<root>
	<config>
		<depend config="../core.min.js.xml">../core.min.js</depend>
		<depend config="../common.min.js.xml">../common.min.js</depend>
		<depend config="comp.min.js.xml">comp.min.js</depend>
		
		<file>justep/dataTables/js/jquery.dataTables.js</file>
		<file>justep/dataTables/js/dataTables.bootstrap.js</file>
		<file>justep/dataTables/js/dataTables.responsive.js</file>
		<file>justep/dataTables/dataTables.config.js</file>
		<file>justep/dataTables/dataTables.js</file>
		<file>bootstrap/panel/panel.js</file>
		<file>bootstrap/accordion/accordion.config.js</file>
		<file>bootstrap/accordion/accordion.js</file>
		<file>bootstrap/table/table.js</file>
		<file>bootstrap/tabs/tab.config.js</file>
		<file>bootstrap/tabs/tab.js</file>
		<file>bootstrap/tabs/tabs.config.js</file>
		<file>bootstrap/tabs/tabs.js</file>
		<file>bootstrap/dropdown/dropdown.config.js</file>
		<file>bootstrap/dropdown/dropdown.js</file>
		<file>bootstrap/navs/navs.config.js</file>
		<file>bootstrap/navs/navs.js</file>
		<file>bootstrap/navbar/navbar.config.js</file>
		<file>bootstrap/navbar/navbar.js</file>
		<file>bootstrap/carousel/carousel.config.js</file>
		<file>bootstrap/carousel/carousel.js</file>
		<file>bootstrap/alert/alert.config.js</file>
		<file>bootstrap/alert/alert.js</file>
		<file>bootstrap/row/row.js</file>
		<file>bootstrap/dialog/dialog.config.js</file>
		<file>bootstrap/dialog/dialog.js</file>
		<file>bootstrap/inputGroup/inputGroup.js</file>
		<file>bootstrap/scrollSpy/scrollSpy.config.js</file>
		<file>bootstrap/scrollSpy/scrollSpy.js</file>
		<file>bootstrap/pagination/pagination.config.js</file>
		<file>bootstrap/pagination/pagination.js</file>
		<file>bootstrap/pager/pager.config.js</file>
		<file>bootstrap/pager/pager.js</file>
		<file>bootstrap/form/form.js</file>
		<file>justep/attachment/attachmentSimple.config.js</file>
		<file>justep/attachment/attachmentSimple.js</file>
		
		<output name="comp2.min.js"/>
	</config>
</root>
